flask_jsontools/__init__.py
flask_jsontools/decorators.py
flask_jsontools/formatting.py
flask_jsontools/response.py
flask_jsontools/testing.py
flask_jsontools/views.py
flask_jsontools-0.1.7.dist-info/LICENSE
flask_jsontools-0.1.7.dist-info/METADATA
flask_jsontools-0.1.7.dist-info/WHEEL
flask_jsontools-0.1.7.dist-info/top_level.txt
flask_jsontools-0.1.7.dist-info/RECORD
