Metadata-Version: 2.1
Name: flask-jsontools
Version: 0.1.7
Summary: JSON API tools for Flask 
Home-page: https://github.com/kolypto/py-flask-jsontools
Author: Mark Vartanyan
Author-email: kolypto@gmail.com
License: BSD
Keywords: flask,json
Platform: any
Classifier: Development Status :: 5 - Production/Stable
Classifier: Intended Audience :: Developers
Classifier: Natural Language :: English
Classifier: Operating System :: OS Independent
Classifier: Programming Language :: Python :: 2
Classifier: Programming Language :: Python :: 3
Classifier: Topic :: Software Development :: Libraries :: Python Modules
Requires-Dist: flask (>=0.10.1)
Requires-Dist: future (>=0.17.1)
